micropytest/__init__.py
micropytest/__main__.py
micropytest/cli.py
micropytest/command.py
micropytest/core.py
micropytest/decorators.py
micropytest/vcs_helper.py
micropytest-0.6.dist-info/licenses/LICENSE
micropytest-0.6.dist-info/METADATA
micropytest-0.6.dist-info/WHEEL
micropytest-0.6.dist-info/entry_points.txt
micropytest-0.6.dist-info/top_level.txt
micropytest-0.6.dist-info/RECORD
