Metadata-Version: 2.4
Name: micropytest
Version: 0.6
Summary: A micro test runner
Author-email: Thomas Fischer <tfischer@beamng.gmbh>
License: MIT
Project-URL: Homepage, https://github.com/BeamNG/micropytest
Project-URL: Issues, https://github.com/BeamNG/micropytest/issues
Project-URL: Changelog, https://github.com/BeamNG/micropytest?tab=readme-ov-file#changelog
Keywords: pytest,micro,test-runner
Classifier: Development Status :: 3 - Alpha
Classifier: Programming Language :: Python :: 3
Classifier: Programming Language :: Python :: 3.4
Classifier: License :: OSI Approved :: MIT License
Classifier: Operating System :: OS Independent
Classifier: Topic :: Software Development :: Testing
Requires-Python: >=3.4
License-File: LICENSE
Provides-Extra: color
Requires-Dist: colorama; extra == "color"
Provides-Extra: progress
Requires-Dist: rich>=10.0.0; extra == "progress"
Dynamic: license-file
